<?xml version="1.0" encoding="UTF-8"?>

<clusters>
			<clusterSet>
			 	    <id>1</id>
					<name><![CDATA[0 at 1 Min]]></name>
					
		<cluster>
					   <id>1.1</id>
					<name><![CDATA[Total]]></name>
					
					<ruleSet>
	                   <predicate>eq</predicate>					
					   <expression>
					         <question>babyApgaronemin</question>
					         <edge>0</edge>
					   </expression>
					   <conjunction>end</conjunction>
					   
					</ruleSet>
		   </cluster>
		         
		   <cluster>
					   <id>1.2</id>
					<name><![CDATA[Not Entered]]></name>
					
					<ruleSet>
	                   <predicate>eq</predicate>					
					   <expression>
					         <question>babyApgaronemin</question>
					         <edge>Unknown</edge>
					   </expression>
					   <conjunction>end</conjunction>
					   
					</ruleSet>
		   </cluster>
		          
	</clusterSet>
				
				
	<clusterSet>
			 <id>2</id>
					<name><![CDATA[<9 at 5 min]]></name>
					
		<cluster>
					   <id>2.1</id>
					<name><![CDATA[Total]]></name>
					
					<ruleSet>
	                   <predicate>lt</predicate>					
					   <expression>
					         <question>babyApgarfivemin</question>
					         <edge>9</edge>
					   </expression>
					   <conjunction>end</conjunction>
					   
					</ruleSet>
       </cluster>
		          
       <cluster>
					   <id>2.2</id>
					<name><![CDATA[Not Entered]]></name>
					
					<ruleSet>
	                   <predicate>eq</predicate>					
					   <expression>
					         <question>babyApgarfivemin</question>
					         <edge>Unknown</edge>
					   </expression>
					   <conjunction>end</conjunction>
					   
					</ruleSet>
	    </cluster>
		          
	</clusterSet>
			
</clusters>

